MANIFEST.in
README.md
setup.cfg
setup.py
VMCloak.egg-info/PKG-INFO
VMCloak.egg-info/SOURCES.txt
VMCloak.egg-info/dependency_links.txt
VMCloak.egg-info/entry_points.txt
VMCloak.egg-info/requires.txt
VMCloak.egg-info/top_level.txt
bin/vmcloak-gethwconf
bin/vmcloak-iptables
bin/vmcloak-killvbox
bin/vmcloak-removevms
bin/vmcloak-vboxnet0
vmcloak/__init__.py
vmcloak/abstract.py
vmcloak/agent.py
vmcloak/conf.py
vmcloak/constants.py
vmcloak/exceptions.py
vmcloak/main.py
vmcloak/misc.py
vmcloak/paths.py
vmcloak/rand.py
vmcloak/repository.py
vmcloak/swarm.py
vmcloak/verify.py
vmcloak/vm.py
vmcloak/win10.py
vmcloak/win7.py
vmcloak/win81.py
vmcloak/winxp.py
vmcloak/data/__init__.py
vmcloak/data/config.py
vmcloak/data/modified_agent.py
vmcloak/data/bootstrap/__init__.py
vmcloak/data/bootstrap/agent.py
vmcloak/data/bootstrap/bootstrap.bat
vmcloak/data/bootstrap/click.exe
vmcloak/data/bootstrap/resolution.py
vmcloak/data/db_migration/alembic.ini
vmcloak/data/db_migration/env.py
vmcloak/data/db_migration/script.py.mako
vmcloak/data/db_migration/versions/add_alembic_version.py
vmcloak/data/db_migration/versions/add_paravirtprovider_column.py
vmcloak/data/hwconf/__init__.py
vmcloak/data/hwconf/hwconf.txt
vmcloak/data/win10/__init__.py
vmcloak/data/win10/autounattend.xml
vmcloak/data/win10/boot.img
vmcloak/data/win7/__init__.py
vmcloak/data/win7/autounattend.xml
vmcloak/data/win7/boot.img
vmcloak/data/win81/__init__.py
vmcloak/data/win81/autounattend.xml
vmcloak/data/win81/boot.img
vmcloak/data/winxp/__init__.py
vmcloak/data/winxp/boot.img
vmcloak/data/winxp/keyboard_layout_values.txt
vmcloak/data/winxp/winnt-opt.sif
vmcloak/data/winxp/winnt.sif
vmcloak/dependencies/__init__.py
vmcloak/dependencies/adobepdf.py
vmcloak/dependencies/chrome.py
vmcloak/dependencies/cuteftp.py
vmcloak/dependencies/dns.py
vmcloak/dependencies/dotnet.py
vmcloak/dependencies/extract.py
vmcloak/dependencies/firefox.py
vmcloak/dependencies/flash.py
vmcloak/dependencies/ie10.py
vmcloak/dependencies/ie11.py
vmcloak/dependencies/ie9.py
vmcloak/dependencies/java.py
vmcloak/dependencies/kb.py
vmcloak/dependencies/modified.py
vmcloak/dependencies/office.py
vmcloak/dependencies/pillow.py
