Metadata-Version: 1.0
Name: VMCloak
Version: 0.4.6
Summary: Automated Virtual Machine Generation and Cloaking for Cuckoo Sandbox.
Home-page: http://vmcloak.org/
Author: Jurriaan Bremer
Author-email: jbr@cuckoo.sh
License: GPLv3
Platform: UNKNOWN
